go2jinja/__init__.py
go2jinja/convert.py
go2jinja-0.2.0.dist-info/licenses/LICENSE
go2jinja-0.2.0.dist-info/METADATA
go2jinja-0.2.0.dist-info/WHEEL
go2jinja-0.2.0.dist-info/top_level.txt
go2jinja-0.2.0.dist-info/zip-safe
go2jinja-0.2.0.dist-info/RECORD
