Metadata-Version: 2.4
Name: go2jinja
Version: 0.2.0
Summary: Library for converting Go Templates to Jinja Templates
Home-page: https://github.com/engelmi/go2jinja
Author: Michael Engel
License: LGPL-2.1-or-later
Keywords: go2jinja,python,Go,template,Jinja
Classifier: Programming Language :: Python
Classifier: Programming Language :: Python :: 3
Requires-Python: >=3.9
License-File: LICENSE
Dynamic: author
Dynamic: classifier
Dynamic: description
Dynamic: description-content-type
Dynamic: home-page
Dynamic: keywords
Dynamic: license
Dynamic: license-file
Dynamic: requires-python
Dynamic: summary
